mcrp_utils/__init__.py
mcrp_utils/test_zip_columns.py
mcrp_utils/timelogger.py
mcrp_utils/utils.py
mcrp_utils-0.2.0.dist-info/LICENSE
mcrp_utils-0.2.0.dist-info/METADATA
mcrp_utils-0.2.0.dist-info/WHEEL
mcrp_utils-0.2.0.dist-info/top_level.txt
mcrp_utils-0.2.0.dist-info/RECORD
